.gitignore
.travis.yml
CHANGELOG.md
LICENSE.TXT
README.rst
setup.py
tox.ini
chattymarkov/__init__.py
chattymarkov.egg-info/PKG-INFO
chattymarkov.egg-info/SOURCES.txt
chattymarkov.egg-info/dependency_links.txt
chattymarkov.egg-info/requires.txt
chattymarkov.egg-info/top_level.txt
chattymarkov/database/__init__.py
chattymarkov/database/base.py
chattymarkov/database/databases.py
examples/memory.py
requirements/base.in
requirements/base.txt
requirements/dev.in
requirements/dev.txt
tests/test_chattymarkov.py
tests/database/test_init.py
tests/database/test_memory.py