Metadata-Version: 1.0
Name: chattymarkov
Version: 1.1.0
Summary: Generate random sentences through markov chains
Home-page: https://github.com/Ge0/chattymarkov
Author: Geoffrey ROYER
Author-email: geoffrey.royer@gmail.com
License: MIT
Platform: UNKNOWN
